[
  {
    "name": "Labatt Brewing Company"
  },
  {
    "name": "Guinness"
  },
  {
    "name": "Heineken"
  },
  {
    "name": "MillerCoors"
  },
  {
    "name": "Boston Beer Company"
  },
  {
    "name": "Stella Artois"
  },
  {
    "name": "Budweiser"
  },
  {
    "name": "Yuengling"
  },
  {
    "name": "Beck's"
  },
  {
    "name": "Fat Tire"
  },
  {
    "name": "Dogfish Head"
  },
  {
    "name": "Hoegaarden"
  },
  {
    "name": "Sierra Nevada Brewing Co."
  },
  {
    "name": "Michelob Brewing Co."
  },
  {
    "name": "Coors Brewing Company"
  },
  {
    "name": "New Castle Brewing"
  },
  {
    "name": "Hiller Brewing Company"
  },
  {
    "name": "Asahi Breweries"
  },
  {
    "name": "Birra Peroni"
  },
  {
    "name": "Pilsner Urquell"
  },
  {
    "name": "Shocktop"
  },
  {
    "name": "Desoes & Geddes"
  },
  {
    "name": "Latrobe Brewing Company"
  },
  {
    "name": "Anheuser-Busch"
  },
  {
    "name": "August Schell Brewing Co."
  },
  {
    "name": "Pabst Brewing Company"
  },
  {
    "name": "Jacob Leinenkugel Brewing Company"
  },
  {
    "name": "Sapporo Breweries"
  },
  {
    "name": "Carlsberg"
  }
]
